ftx/__init__.py
ftx/authentication.py
ftx/client.py
ftx/enums.py
ftx/exceptions.py
ftx/streams.py
ftx/threaded_stream.py
ftx/timer.py
python_ftx-0.1.2.dist-info/LICENSE
python_ftx-0.1.2.dist-info/METADATA
python_ftx-0.1.2.dist-info/WHEEL
python_ftx-0.1.2.dist-info/top_level.txt
python_ftx-0.1.2.dist-info/zip-safe
python_ftx-0.1.2.dist-info/RECORD
